jsonextended/__init__.py
jsonextended/edict.py
jsonextended/ejson.py
jsonextended/example_mockpaths.py
jsonextended/mockpath.py
jsonextended/plugins.py
jsonextended/utils.py
jsonextended/_example_data_folder/__init__.py
jsonextended/_example_data_folder/data.crystal.out
jsonextended/_example_data_folder/file1.keypair
jsonextended/_example_data_folder/dir1/__init__.py
jsonextended/_example_data_folder/dir1/file1.json
jsonextended/_example_data_folder/dir1/file2.json
jsonextended/_example_data_folder/dir1/dir1_1/__init__.py
jsonextended/_example_data_folder/dir1/dir1_1/file1_1.json
jsonextended/_example_data_folder/dir2/__init__.py
jsonextended/_example_data_folder/dir2/file1.csv
jsonextended/_example_data_folder/dir2/file1.json
jsonextended/_example_data_folder/dir3/__init__.py
jsonextended/_example_data_folder/dir3/empty.data
jsonextended/encoders/__init__.py
jsonextended/encoders/decimals.py
jsonextended/encoders/fraction.py
jsonextended/encoders/ndarray.py
jsonextended/encoders/pint_quantity.py
jsonextended/encoders/set.py
jsonextended/parsers/__init__.py
jsonextended/parsers/csvs.py
jsonextended/parsers/csvs_literal.py
jsonextended/parsers/hdf5.py
jsonextended/parsers/ipynb.py
jsonextended/parsers/jsons.py
jsonextended/parsers/keypairs.py
jsonextended/parsers/yaml.py
jsonextended/units/__init__.py
jsonextended/units/core.py
jsonextended-0.7.11.dist-info/LICENSE
jsonextended-0.7.11.dist-info/METADATA
jsonextended-0.7.11.dist-info/WHEEL
jsonextended-0.7.11.dist-info/top_level.txt
jsonextended-0.7.11.dist-info/zip-safe
jsonextended-0.7.11.dist-info/RECORD
